{
    "align_labels_right": 0,
    "creation": "2026-01-26 23:55:00.000000",
    "default_print_language": "en",
    "disabled": 0,
    "doc_type": "Quality Inspection",
    "docstatus": 0,
    "doctype": "Print Format",
    "font_size": 11,
    "line_breaks": 0,
    "margin_bottom": 10.0,
    "margin_left": 10.0,
    "margin_right": 10.0,
    "margin_top": 10.0,
    "modified": "2026-01-26 23:55:00.000000",
    "modified_by": "Administrator",
    "module": "DressUp",
    "name": "Quality Inspection Premium",
    "owner": "Administrator",
    "print_format_builder": 0,
    "print_format_type": "Jinja",
    "raw_printing": 0,
    "show_section_headings": 0,
    "standard": "Yes"
}
